imgx/__init__.py
imgx/cli.py
imgx/imgx.py
imgx/process_module.py
imgx-0.1.3.dist-info/AUTHORS.rst
imgx-0.1.3.dist-info/LICENSE
imgx-0.1.3.dist-info/METADATA
imgx-0.1.3.dist-info/WHEEL
imgx-0.1.3.dist-info/entry_points.txt
imgx-0.1.3.dist-info/top_level.txt
imgx-0.1.3.dist-info/RECORD
