Metadata-Version: 2.1
Name: imgx
Version: 0.1.3
Summary: Image processing package
Home-page: https://github.com/M-Farag/imgx
Author: Mina Amin
Author-email: mina.farag@icloud.com
License: MIT license
Keywords: imgx
Classifier: Development Status :: 2 - Pre-Alpha
Classifier: Intended Audience :: Developers
Classifier: License :: OSI Approved :: MIT License
Classifier: Natural Language :: English
Classifier: Programming Language :: Python :: 3
Classifier: Programming Language :: Python :: 3.6
Classifier: Programming Language :: Python :: 3.7
Classifier: Programming Language :: Python :: 3.8
Requires-Python: >=3.6
License-File: LICENSE
License-File: AUTHORS.rst
Requires-Dist: Click >=7.0
Requires-Dist: Pillow >=8.0
Requires-Dist: piexif
Requires-Dist: shutil
Requires-Dist: pathlib
